rarego_kge/__init__.py
rarego_kge/example.py
rarego_kge/module.py
rarego_kge/utils.py
rarego_kge/data/R25KG-Rare-Gene.tsv
rarego_kge/data/R25KG-Rare.tsv
rarego_kge/drugrepurposing/__init__.py
rarego_kge/drugrepurposing/repurpose_by_disease_id.py
rarego_kge/drugrepurposing/repurpose_by_drug_ids.py
rarego_kge/drugrepurposing/repurpose_by_fda_drug_names.py
rarego_kge/drugrepurposing/repurpose_by_gene_ids.py
rarego_kge/example_trainings/__init__.py
rarego_kge/kgsearch/__init__.py
rarego_kge/kgsearch/gridsearch.py
rarego_kge/kgsearch/gridsearch2.py
rarego_kge/kgsearch/gridsearch3.py
rarego_kge/training_code/KGEtrainclass.py
rarego_kge/training_code/__init__.py
rarego_kge/training_code/config.py
rarego_kge/training_code/kgIO.py
RareGO-0.0.33.dist-info/LICENSE.txt
RareGO-0.0.33.dist-info/METADATA
RareGO-0.0.33.dist-info/WHEEL
RareGO-0.0.33.dist-info/top_level.txt
RareGO-0.0.33.dist-info/RECORD
